<annotation>
	<folder>sheep</folder>
	<filename>sheep_image (128).jpg</filename>
	<path>C:\Users\mani\Desktop\sheep\sheep_image (128).jpg</path>
	<source>
		<database>Unknown</database>
	</source>
	<size>
		<width>259</width>
		<height>194</height>
		<depth>3</depth>
	</size>
	<segmented>0</segmented>
	<object>
		<name>sheep</name>
		<pose>Unspecified</pose>
		<truncated>0</truncated>
		<difficult>0</difficult>
		<bndbox>
			<xmin>142</xmin>
			<ymin>89</ymin>
			<xmax>175</xmax>
			<ymax>118</ymax>
		</bndbox>
	</object>
	<object>
		<name>sheep</name>
		<pose>Unspecified</pose>
		<truncated>0</truncated>
		<difficult>0</difficult>
		<bndbox>
			<xmin>182</xmin>
			<ymin>83</ymin>
			<xmax>208</xmax>
			<ymax>107</ymax>
		</bndbox>
	</object>
	<object>
		<name>sheep</name>
		<pose>Unspecified</pose>
		<truncated>0</truncated>
		<difficult>0</difficult>
		<bndbox>
			<xmin>173</xmin>
			<ymin>77</ymin>
			<xmax>189</xmax>
			<ymax>99</ymax>
		</bndbox>
	</object>
	<object>
		<name>sheep</name>
		<pose>Unspecified</pose>
		<truncated>0</truncated>
		<difficult>0</difficult>
		<bndbox>
			<xmin>130</xmin>
			<ymin>78</ymin>
			<xmax>151</xmax>
			<ymax>97</ymax>
		</bndbox>
	</object>
	<object>
		<name>sheep</name>
		<pose>Unspecified</pose>
		<truncated>0</truncated>
		<difficult>0</difficult>
		<bndbox>
			<xmin>102</xmin>
			<ymin>79</ymin>
			<xmax>124</xmax>
			<ymax>102</ymax>
		</bndbox>
	</object>
	<object>
		<name>sheep</name>
		<pose>Unspecified</pose>
		<truncated>0</truncated>
		<difficult>0</difficult>
		<bndbox>
			<xmin>62</xmin>
			<ymin>75</ymin>
			<xmax>80</xmax>
			<ymax>93</ymax>
		</bndbox>
	</object>
	<object>
		<name>sheep</name>
		<pose>Unspecified</pose>
		<truncated>0</truncated>
		<difficult>0</difficult>
		<bndbox>
			<xmin>19</xmin>
			<ymin>69</ymin>
			<xmax>29</xmax>
			<ymax>82</ymax>
		</bndbox>
	</object>
</annotation>
