<annotation>
	<folder>rem</folder>
	<filename>sheep_image (95).jpg</filename>
	<path>C:\Users\mani\Desktop\rem\sheep_image (95).jpg</path>
	<source>
		<database>Unknown</database>
	</source>
	<size>
		<width>275</width>
		<height>183</height>
		<depth>3</depth>
	</size>
	<segmented>0</segmented>
	<object>
		<name>sheep</name>
		<pose>Unspecified</pose>
		<truncated>0</truncated>
		<difficult>0</difficult>
		<bndbox>
			<xmin>106</xmin>
			<ymin>49</ymin>
			<xmax>243</xmax>
			<ymax>136</ymax>
		</bndbox>
	</object>
</annotation>
