<annotation>
	<folder>sheep</folder>
	<filename>videoblocks-aerial-view-of-sheep-being-moved-on-farm-using-sheep-dogs-new-zealand_r1zckcjsj7_thumbnail-small01.jpg</filename>
	<path>C:\Users\Sanusi\Documents\Sheep\sheep\videoblocks-aerial-view-of-sheep-being-moved-on-farm-using-sheep-dogs-new-zealand_r1zckcjsj7_thumbnail-small01.jpg</path>
	<source>
		<database>Unknown</database>
	</source>
	<size>
		<width>320</width>
		<height>180</height>
		<depth>3</depth>
	</size>
	<segmented>0</segmented>
	<object>
		<name>sheep</name>
		<pose>Unspecified</pose>
		<truncated>0</truncated>
		<difficult>0</difficult>
		<bndbox>
			<xmin>251</xmin>
			<ymin>95</ymin>
			<xmax>263</xmax>
			<ymax>107</ymax>
		</bndbox>
	</object>
	<object>
		<name>sheep</name>
		<pose>Unspecified</pose>
		<truncated>0</truncated>
		<difficult>0</difficult>
		<bndbox>
			<xmin>265</xmin>
			<ymin>97</ymin>
			<xmax>271</xmax>
			<ymax>110</ymax>
		</bndbox>
	</object>
	<object>
		<name>sheep</name>
		<pose>Unspecified</pose>
		<truncated>0</truncated>
		<difficult>0</difficult>
		<bndbox>
			<xmin>126</xmin>
			<ymin>117</ymin>
			<xmax>136</xmax>
			<ymax>130</ymax>
		</bndbox>
	</object>
	<object>
		<name>sheep</name>
		<pose>Unspecified</pose>
		<truncated>0</truncated>
		<difficult>0</difficult>
		<bndbox>
			<xmin>89</xmin>
			<ymin>142</ymin>
			<xmax>99</xmax>
			<ymax>162</ymax>
		</bndbox>
	</object>
	<object>
		<name>sheep</name>
		<pose>Unspecified</pose>
		<truncated>0</truncated>
		<difficult>0</difficult>
		<bndbox>
			<xmin>95</xmin>
			<ymin>145</ymin>
			<xmax>104</xmax>
			<ymax>167</ymax>
		</bndbox>
	</object>
	<object>
		<name>sheep</name>
		<pose>Unspecified</pose>
		<truncated>0</truncated>
		<difficult>0</difficult>
		<bndbox>
			<xmin>125</xmin>
			<ymin>142</ymin>
			<xmax>133</xmax>
			<ymax>156</ymax>
		</bndbox>
	</object>
	<object>
		<name>sheep</name>
		<pose>Unspecified</pose>
		<truncated>0</truncated>
		<difficult>0</difficult>
		<bndbox>
			<xmin>105</xmin>
			<ymin>137</ymin>
			<xmax>113</xmax>
			<ymax>156</ymax>
		</bndbox>
	</object>
	<object>
		<name>sheep</name>
		<pose>Unspecified</pose>
		<truncated>0</truncated>
		<difficult>0</difficult>
		<bndbox>
			<xmin>163</xmin>
			<ymin>146</ymin>
			<xmax>171</xmax>
			<ymax>158</ymax>
		</bndbox>
	</object>
	<object>
		<name>sheep</name>
		<pose>Unspecified</pose>
		<truncated>0</truncated>
		<difficult>0</difficult>
		<bndbox>
			<xmin>143</xmin>
			<ymin>117</ymin>
			<xmax>152</xmax>
			<ymax>128</ymax>
		</bndbox>
	</object>
	<object>
		<name>sheep</name>
		<pose>Unspecified</pose>
		<truncated>0</truncated>
		<difficult>0</difficult>
		<bndbox>
			<xmin>151</xmin>
			<ymin>113</ymin>
			<xmax>159</xmax>
			<ymax>124</ymax>
		</bndbox>
	</object>
	<object>
		<name>sheep</name>
		<pose>Unspecified</pose>
		<truncated>0</truncated>
		<difficult>0</difficult>
		<bndbox>
			<xmin>144</xmin>
			<ymin>139</ymin>
			<xmax>159</xmax>
			<ymax>152</ymax>
		</bndbox>
	</object>
	<object>
		<name>sheep</name>
		<pose>Unspecified</pose>
		<truncated>0</truncated>
		<difficult>0</difficult>
		<bndbox>
			<xmin>161</xmin>
			<ymin>135</ymin>
			<xmax>173</xmax>
			<ymax>147</ymax>
		</bndbox>
	</object>
	<object>
		<name>sheep</name>
		<pose>Unspecified</pose>
		<truncated>0</truncated>
		<difficult>0</difficult>
		<bndbox>
			<xmin>208</xmin>
			<ymin>135</ymin>
			<xmax>219</xmax>
			<ymax>150</ymax>
		</bndbox>
	</object>
	<object>
		<name>sheep</name>
		<pose>Unspecified</pose>
		<truncated>0</truncated>
		<difficult>0</difficult>
		<bndbox>
			<xmin>220</xmin>
			<ymin>130</ymin>
			<xmax>227</xmax>
			<ymax>144</ymax>
		</bndbox>
	</object>
	<object>
		<name>sheep</name>
		<pose>Unspecified</pose>
		<truncated>0</truncated>
		<difficult>0</difficult>
		<bndbox>
			<xmin>232</xmin>
			<ymin>122</ymin>
			<xmax>243</xmax>
			<ymax>131</ymax>
		</bndbox>
	</object>
	<object>
		<name>sheep</name>
		<pose>Unspecified</pose>
		<truncated>0</truncated>
		<difficult>0</difficult>
		<bndbox>
			<xmin>223</xmin>
			<ymin>111</ymin>
			<xmax>233</xmax>
			<ymax>119</ymax>
		</bndbox>
	</object>
	<object>
		<name>sheep</name>
		<pose>Unspecified</pose>
		<truncated>0</truncated>
		<difficult>0</difficult>
		<bndbox>
			<xmin>175</xmin>
			<ymin>148</ymin>
			<xmax>182</xmax>
			<ymax>162</ymax>
		</bndbox>
	</object>
	<object>
		<name>sheep</name>
		<pose>Unspecified</pose>
		<truncated>0</truncated>
		<difficult>0</difficult>
		<bndbox>
			<xmin>190</xmin>
			<ymin>147</ymin>
			<xmax>196</xmax>
			<ymax>166</ymax>
		</bndbox>
	</object>
	<object>
		<name>sheep</name>
		<pose>Unspecified</pose>
		<truncated>0</truncated>
		<difficult>0</difficult>
		<bndbox>
			<xmin>132</xmin>
			<ymin>93</ymin>
			<xmax>141</xmax>
			<ymax>105</ymax>
		</bndbox>
	</object>
	<object>
		<name>sheep</name>
		<pose>Unspecified</pose>
		<truncated>0</truncated>
		<difficult>0</difficult>
		<bndbox>
			<xmin>132</xmin>
			<ymin>84</ymin>
			<xmax>140</xmax>
			<ymax>94</ymax>
		</bndbox>
	</object>
	<object>
		<name>sheep</name>
		<pose>Unspecified</pose>
		<truncated>0</truncated>
		<difficult>0</difficult>
		<bndbox>
			<xmin>132</xmin>
			<ymin>160</ymin>
			<xmax>148</xmax>
			<ymax>171</ymax>
		</bndbox>
	</object>
	<object>
		<name>sheep</name>
		<pose>Unspecified</pose>
		<truncated>0</truncated>
		<difficult>0</difficult>
		<bndbox>
			<xmin>152</xmin>
			<ymin>161</ymin>
			<xmax>167</xmax>
			<ymax>174</ymax>
		</bndbox>
	</object>
	<object>
		<name>sheep</name>
		<pose>Unspecified</pose>
		<truncated>0</truncated>
		<difficult>0</difficult>
		<bndbox>
			<xmin>106</xmin>
			<ymin>157</ymin>
			<xmax>115</xmax>
			<ymax>176</ymax>
		</bndbox>
	</object>
	<object>
		<name>sheep</name>
		<pose>Unspecified</pose>
		<truncated>0</truncated>
		<difficult>0</difficult>
		<bndbox>
			<xmin>136</xmin>
			<ymin>136</ymin>
			<xmax>144</xmax>
			<ymax>151</ymax>
		</bndbox>
	</object>
	<object>
		<name>sheep</name>
		<pose>Unspecified</pose>
		<truncated>0</truncated>
		<difficult>0</difficult>
		<bndbox>
			<xmin>208</xmin>
			<ymin>156</ymin>
			<xmax>215</xmax>
			<ymax>172</ymax>
		</bndbox>
	</object>
	<object>
		<name>sheep</name>
		<pose>Unspecified</pose>
		<truncated>0</truncated>
		<difficult>0</difficult>
		<bndbox>
			<xmin>221</xmin>
			<ymin>153</ymin>
			<xmax>227</xmax>
			<ymax>170</ymax>
		</bndbox>
	</object>
	<object>
		<name>sheep</name>
		<pose>Unspecified</pose>
		<truncated>0</truncated>
		<difficult>0</difficult>
		<bndbox>
			<xmin>246</xmin>
			<ymin>144</ymin>
			<xmax>251</xmax>
			<ymax>159</ymax>
		</bndbox>
	</object>
	<object>
		<name>sheep</name>
		<pose>Unspecified</pose>
		<truncated>0</truncated>
		<difficult>0</difficult>
		<bndbox>
			<xmin>226</xmin>
			<ymin>132</ymin>
			<xmax>233</xmax>
			<ymax>149</ymax>
		</bndbox>
	</object>
	<object>
		<name>sheep</name>
		<pose>Unspecified</pose>
		<truncated>0</truncated>
		<difficult>0</difficult>
		<bndbox>
			<xmin>173</xmin>
			<ymin>162</ymin>
			<xmax>189</xmax>
			<ymax>178</ymax>
		</bndbox>
	</object>
	<object>
		<name>sheep</name>
		<pose>Unspecified</pose>
		<truncated>0</truncated>
		<difficult>0</difficult>
		<bndbox>
			<xmin>193</xmin>
			<ymin>162</ymin>
			<xmax>206</xmax>
			<ymax>176</ymax>
		</bndbox>
	</object>
	<object>
		<name>sheep</name>
		<pose>Unspecified</pose>
		<truncated>0</truncated>
		<difficult>0</difficult>
		<bndbox>
			<xmin>253</xmin>
			<ymin>138</ymin>
			<xmax>259</xmax>
			<ymax>153</ymax>
		</bndbox>
	</object>
	<object>
		<name>sheep</name>
		<pose>Unspecified</pose>
		<truncated>0</truncated>
		<difficult>0</difficult>
		<bndbox>
			<xmin>250</xmin>
			<ymin>116</ymin>
			<xmax>257</xmax>
			<ymax>131</ymax>
		</bndbox>
	</object>
</annotation>
